rtl/Resultmux.sv
module Resultmux(
    input [31:0] ALU_i,
    input [31:0] Mem_i,
    input [31:0] PC_i,
    input [31:0] PCtarget_i,
    input [1:0] ResultSrc_i,
    output reg [31:0] Result_o
);

always_comb begin
    
    case(ResultSrc_i)

    0: Result_o = ALU_i;
    1: Result_o = Mem_i;
    2: Result_o = PC_i + 4; //changed this line, because we need to save the address of the NEXT instruction
    3: Result_o = PCtarget_i;
    default: Result_o = ALU_i;
    
    endcase

end

endmodule

rtl/DataMem.sv
module DataMem(
    input clk,
    input [31:0] ioin1,
    input [31:0] ioin2,
    input [31:0] a,
    input  [31:0] wd,
    input [2:0] funct3, //byte, half, word
    input we,
    output reg [31:0] rd
);

//how can we implement byte-addressable memory?

bit [7:0] Memory [bit[31:0]];


always_ff@(posedge clk) begin
    if(we) begin //store  
        case(funct3)
            0: {Memory[a]} <= wd[7:0]; //sb
            1: {Memory[a+1], Memory[a]} <= wd[15:0]; //sh
            2: {Memory[a+3], Memory[a+2], Memory[a+1], Memory[a]} <= wd; //sw
            default: {Memory[a+3], Memory[a+2], Memory[a+1], Memory[a]} <= wd; //sw
        endcase
    end
end

always_comb begin
     //load
    if(a > 32'hBFC00FFF)begin
            if(a == 32'hFFFFFFFF) 
                rd = ioin1;
            else // should be used with 0xFFFFFFDF
                rd = ioin2;
        end
    else
        case(funct3)
            0: rd = {{24{Memory[a][7]}}, Memory[a]}; //lb
            1: rd = {{16{Memory[a+1][7]}}, Memory[a+1], Memory[a]}; // lh
            2: rd = {Memory[a+3], Memory[a+2], Memory[a+1], Memory[a]}; //lw
            4: rd = {{24{1'b0}}, Memory[a]}; //lbu
            5: rd = {{16{1'b0}}, Memory[a+1], Memory[a]}; //lhu
            default: rd = {Memory[a+3], Memory[a+2], Memory[a+1], Memory[a]}; //lw
        endcase
end

endmodule

rtl/PCTarget.sv
module PCTarget(
    input [31:0] ImmOp_i,
    input [31:0] PC_i,
    output [31:0] pcTarget_o
);

assign pcTarget_o = PC_i + ImmOp_i;

endmodule

rtl/ALU.sv
module ALU (
    input [4:0] ALUCtrl_i, //we got 13 cases
    input [31:0] SrcA_i,
    input [31:0] SrcB_i,
    output reg [31:0] ALUResult_o,
    output [2:0] Flags_o 
);

/////////// Signed Logic /////////////////////////

logic signed [31:0] SrcA_s, SrcB_s; 

assign SrcA_s = SrcA_i;
assign SrcB_s = SrcB_i;

////////////// Instructions ////////////////////////

always_comb begin

    case(ALUCtrl_i)
    0: ALUResult_o = SrcA_s + SrcB_s; //add
    1: ALUResult_o = SrcA_s - SrcB_s; //sub
    2: ALUResult_o = SrcA_s << SrcB_s[4:0]; //SLL reg
    3: ALUResult_o = SrcA_s << SrcB_s; // SLL imm
    4: ALUResult_o = {{31{1'b0}},(SrcA_s < SrcB_s)};  //SLT
    5: ALUResult_o = {{31{1'b0}}, (SrcA_i < SrcB_i)}; // SLT unsigned
    6: ALUResult_o = SrcA_s ^ SrcB_s; // xor
    7: ALUResult_o = SrcA_s >> SrcB_s[4:0]; // SRL reg
    8: ALUResult_o = SrcA_s >>> SrcB_s[4:0]; // SRA reg
    9: ALUResult_o = SrcA_s >> SrcB_s; // SRL imm
    10: ALUResult_o = SrcA_s >>> SrcB_s; // SRA imm
    11: ALUResult_o = SrcA_s | SrcB_s; // or
    12: ALUResult_o = SrcA_s & SrcB_s; // and 
    13: ALUResult_o = SrcB_i; // u-type instr
    default: ALUResult_o = SrcA_s + SrcB_s;

    endcase

    Flags_o = {(ALUResult_o == 0), (SrcA_s >= SrcB_s), (SrcA_i >= SrcB_i)}; //zero, gt, gtu

end


endmodule

rtl/ALUmux.sv
module ALUmux(
    input [31:0] RegOp_i,
    input [31:0] ImmOp_i,
    input ALUsrc_i,
    output reg [31:0] ALUop_o
);

always_comb begin
    if(ALUsrc_i) ALUop_o = ImmOp_i;
    else ALUop_o = RegOp_i;
end 

endmodule

rtl/SignExtend.sv
module SignExtend(
    input [31:0] instr_i,
    input [2:0] ImmSrc_i,
    output reg [31:0] ImmOp_o
);

//update ImmSrc_i

always_comb begin

    case(ImmSrc_i)
    
    0: ImmOp_o = {{20{instr_i[31]}}, instr_i[31:20]}; // i-type
    1:ImmOp_o = {{20{instr_i[31]}}, instr_i[31:25], instr_i[11:7]}; //s-type
    2: ImmOp_o = {{20{instr_i[31]}}, instr_i[7], instr_i[30:25], instr_i[11:8], 1'b0}; //b-type
    3: ImmOp_o = {{12{instr_i[31]}}, instr_i[19:12], instr_i[20], instr_i[30:21], 1'b0}; // j-type
    4: ImmOp_o = {instr_i[31:12], 12'b0}; // u-type
    default: ImmOp_o = 0;

    endcase 

end

endmodule

rtl/RegFile.sv
module RegFile(
    input clk,
    input [4:0] AD1,
    input [4:0] AD2,
    input [4:0] AD3,
    input WE3,
    input [31:0] WD3,
    output reg [31:0] RD1,
    output reg [31:0] RD2,
    output [31:0] a0,
    output [31:0] a1,
    output [31:0] t0,
    output [31:0] t1,
    output [31:0] t5,
    output [31:0] t6 
);

bit [31:0] registers[31];

assign a0 = registers[10-1];
assign a1 = registers[11-1];
assign t0 = registers[5-1];
assign t1 = registers[6-1];
assign t5 = registers[30-2];
assign t6 = registers[31-1];

always_ff @(negedge clk) begin
    if(WE3 && AD3 != 0) registers[AD3-1] <= WD3; 
end

always_comb begin
    if(AD1!=0) RD1 = registers[AD1-1];
    else RD1 = 0;
    if(AD2!=0) RD2 = registers[AD2-1]; 
    else RD2 = 0;
end

endmodule

rtl/ControlUnit.sv
module ControlUnit(
    input [2:0] Flags_i, //flags
    input [31:0] Instr_i, 
    output reg [2:0] funct3,
    output reg RegWrite_o, //register write enable
    output reg ALUsrc_o, //use imm or RD2
    output reg MemWrite_o, // memory write enable
    output reg [2:0] ImmSrc_o, //determine imm-type
    output reg [4:0] ALUctrl_o, //determine alu-op
    output reg [1:0] PCsrc_o, // PC+4 ,PC+imm, rs1+imm
    output reg [1:0] ResultSrc_o // ALU result, Data memory, PC+4
);

///////////// Internal Signals /////////////////////////////

logic [6:0] op; logic funct7; //opcodes logic [2:0] funct3;
logic zero; logic gt; logic gtu; //flags
logic branch; // branch

assign {op, funct3, funct7} = {Instr_i[6:0], Instr_i[14:12], Instr_i[30]}; 
assign {zero, gt, gtu} = Flags_i;

///////////// RegWrite, ALUSrc, Memwrite, PCSrc ////////////////////////

always_comb begin
    RegWrite_o = (op == 3) || (op == 19) || (op == 51) || (op == 55) || (op == 103) || (op == 111); //all except b-type and s-type
    ALUsrc_o = (op == 3) || (op==19) || (op==35) || (op==55) || (op==103); //all except r-type and b-type
    MemWrite_o = (op == 35); // s-type

    if(op == 103) PCsrc_o = 2; //jalr
    else if (branch | op == 111) PCsrc_o = 1; //jal and b-type
    else PCsrc_o = 0;
end

always_comb begin

    case(op)

        ////////////////// r-type and i-type  ////////////////
        51, 19: begin  
            ResultSrc_o = 0; // ALU result
            ImmSrc_o = 0; // for i-type
            branch = 0;
            
            if(op[5]) ALUsrc_o = 0; //rd2
            else ALUsrc_o = 1; //imm

            case(funct3)
            0: begin
                if(op[5]) begin 
                    if(funct7 == 0) ALUctrl_o = 0;
                    else ALUctrl_o = 1;
                end
                else ALUctrl_o = 0;
                end
            1: begin if(op[5]) ALUctrl_o = 2;
                    else ALUctrl_o = 3;
                end 
            2: ALUctrl_o = 4;
            3: ALUctrl_o = 5;
            4: ALUctrl_o = 6;
            5: begin 
                if(op[5]) begin
                    if(funct7 == 0) ALUctrl_o = 7;
                    else ALUctrl_o = 8;
                end
                else begin 
                    if(funct7 == 0) ALUctrl_o = 9;
                    else ALUctrl_o = 10;
                end
            end 
            6: ALUctrl_o = 11;
            7: ALUctrl_o = 12;

            default: ALUctrl_o = 0;
            endcase
        end

        /////////////////// b-type ///////////////////////

        99: begin
            
            ALUsrc_o = 0; //reg
            ALUctrl_o = 1; //x cause flags
            ImmSrc_o = 2; // 13-bit immediate
            ResultSrc_o = 0; //x

            case(funct3)

            0: begin ///////////////beq
                if(zero) branch = 0;
                else branch = 1;
            end
            1: begin ///////////////bne
                if(~zero) branch = 1;
                else branch = 0;
            end
            4: begin //////////////blt
                if(~gt) branch = 1;
                else branch = 0;
            end
            5: begin ///////////////bge
                if(gt) branch = 1;
                else branch = 0;
            end
            6:begin ////////////////bltu
                if(~gtu) branch = 1;
                else branch = 0;
            end
            7:begin /////////////// bgtu
                if(gtu) branch = 1;
                else branch = 0;
            end

            endcase

        end

        /////////////////////// l-type and s-type ////////////

        3, 35: begin ///lw and sw
        ALUctrl_o = 0; //add
        ALUsrc_o = 1; //imm
        ImmSrc_o = {2'b00, funct7}; //0 for lw and 1 for sw
        ResultSrc_o = 1; //important for lw
        branch = 0;
        end

        ////// j-type and u-type /////////////

        103, 111: begin //jalr and jal
        ALUsrc_o = 1; //imm
        ALUctrl_o = 0; //add
        ImmSrc_o = {1'b0, {2{op[3]}}}; // 0 for jalr, 3 for jal
        ResultSrc_o = 2; //pc+4
        branch = 0;
        end

        23, 55: begin //auipc, lui
        ALUsrc_o = 1; //imm
        ALUctrl_o = 13; //u-type
        ImmSrc_o = 4; //u-type
        ResultSrc_o = {2{funct7}}; // 3 (pc+imm) for auipc, 0 (alu) for lui
        branch = 0;
        end

    endcase

end 


endmodule

rtl/InstrMem.sv
module InstrMem(
    input [31:0] a,
    output [31:0] rd 
);

bit [31:0] ram_array [bit[31:0]]; //2^32 -1

initial begin
    $display("Loading program.");
    $readmemh("counter.mem", ram_array);
end

assign rd = ram_array[a];

endmodule

rtl/PC.sv
module PC(
    input clk,
    input rst,
    input [1:0] PCsrc_i,
    input [31:0] PCtarget_i,
    input [31:0] PCalu_i,
    output reg [31:0] pc_o
);

logic [31:0] next_PC;

always_ff @(posedge clk) begin
    if(rst) pc_o <= 0;
    else pc_o <= next_PC;
end

always_comb begin

    case(PCsrc_i)
    0: next_PC = pc_o + 4;
    1: next_PC = PCtarget_i;
    2: next_PC = PCalu_i;
    default: next_PC = pc_o + 4;
    endcase

end 

endmodule

rtl/CPU.sv
module CPU(
    input clk,
    input rst,
    input [31:0] ioin1,
    input [31:0] ioin2,
    output [31:0] a0,
    output [31:0] a1,
    output [31:0] t0,
    output [31:0] t1,
    output [31:0] t5,
    output [31:0] t6
);

//////////// fetch ///////////////

// Signals for PC
logic [31:0] pc, instr, pcTarget;

PC programCounter (.clk(clk), .rst(rst), .PCsrc_i(pcsrc), 
.PCtarget_i(pcTarget), .pc_o(pc), .PCalu_i(alu_result)); //careful about pipelining PCTarget

// Fetch instruction
InstrMem instructions(.a(pc), .rd(instr));

//////////// Decode //////////////

//Signals for control unit
logic alusrc, regwrite, memwrite;
logic [1:0] resultsrc, pcsrc;
logic [2:0] flags, funct3, immsrc;
logic [4:0] aluctrl;

ControlUnit control(.Flags_i(flags), .Instr_i(instr), 
.RegWrite_o(regwrite), .ALUsrc_o(alusrc), .ALUctrl_o(aluctrl), .ImmSrc_o(immsrc), 
.MemWrite_o(memwrite), .ResultSrc_o(resultsrc), .PCsrc_o(pcsrc), .funct3(funct3));

// Register file signals
logic [31:0] rd1, rd2, imm_op;
logic [4:0] rs1, rs2, rd;
assign rs1 = instr[19:15];
assign rs2 = instr[24:20];
assign rd = instr[11:7];

// Instantiate Register File
RegFile regfile(.clk(clk), .AD1(rs1), .AD2(rs2), 
    .AD3(rd), .WE3(regwrite), .WD3(result), .RD1(rd1), //wd3
    .RD2(rd2), .a0(a0), .a1(a1), .t0(t0), .t1(t1), .t5(t5),.t6(t6));

SignExtend extend( .instr_i(instr), .ImmSrc_i(immsrc), .ImmOp_o(imm_op));

//////////// Execute ///////////////

// ALU signals
logic [31:0] src_b, alu_result;

ALUmux alu_mux(.RegOp_i(rd2), .ImmOp_i(imm_op), .ALUsrc_i(alusrc), .ALUop_o(src_b));

ALU alu(.ALUCtrl_i(aluctrl), .SrcA_i(rd1), .SrcB_i(src_b), .ALUResult_o(alu_result),
 .Flags_o(flags));

PCTarget target(.ImmOp_i(imm_op), .PC_i(pc), .pcTarget_o(pcTarget));

/////////// Memory //////////////

// Memory signals
logic [31:0] mem_data;

DataMem dataMem(.clk(clk), .a(alu_result), .wd(rd2), .we(memwrite), .rd(mem_data), .funct3(funct3), .ioin1(ioin1), .ioin2(ioin2));

/////////// Writeback //////////////
logic [31:0] result;

Resultmux result_mux( .ALU_i(alu_result), .Mem_i(mem_data), .PC_i(pc), .PCtarget_i(pcTarget),
    .ResultSrc_i(resultsrc), .Result_o(result));

endmodule

rtl/cpu.vcd
$version Generated by VerilatedVcd $end
$date Wed Aug 21 17:42:48 2024 $end
$timescale 1ps $end

 $scope module TOP $end
  $var wire 32 ^ a0 [31:0] $end
  $var wire 32 _ a1 [31:0] $end
  $var wire  1 Z clk $end
  $var wire 32 \ ioin1 [31:0] $end
  $var wire 32 ] ioin2 [31:0] $end
  $var wire  1 [ rst $end
  $var wire 32 ` t0 [31:0] $end
  $var wire 32 a t1 [31:0] $end
  $var wire 32 b t5 [31:0] $end
  $var wire 32 c t6 [31:0] $end
  $scope module CPU $end
   $var wire 32 ^ a0 [31:0] $end
   $var wire 32 _ a1 [31:0] $end
   $var wire 32 T alu_result [31:0] $end
   $var wire  5 ) aluctrl [4:0] $end
   $var wire  1 d alusrc $end
   $var wire  1 Z clk $end
   $var wire  3 R flags [2:0] $end
   $var wire  3 ' funct3 [2:0] $end
   $var wire 32 * imm_op [31:0] $end
   $var wire  3 ( immsrc [2:0] $end
   $var wire 32 $ instr [31:0] $end
   $var wire 32 \ ioin1 [31:0] $end
   $var wire 32 ] ioin2 [31:0] $end
   $var wire 32 U mem_data [31:0] $end
   $var wire  1 P memwrite $end
   $var wire 32 # pc [31:0] $end
   $var wire 32 % pcTarget [31:0] $end
   $var wire  2 Q pcsrc [1:0] $end
   $var wire  5 - rd [4:0] $end
   $var wire 32 e rd1 [31:0] $end
   $var wire 32 f rd2 [31:0] $end
   $var wire  1 O regwrite $end
   $var wire 32 g result [31:0] $end
   $var wire  2 & resultsrc [1:0] $end
   $var wire  5 + rs1 [4:0] $end
   $var wire  5 , rs2 [4:0] $end
   $var wire  1 [ rst $end
   $var wire 32 S src_b [31:0] $end
   $var wire 32 ` t0 [31:0] $end
   $var wire 32 a t1 [31:0] $end
   $var wire 32 b t5 [31:0] $end
   $var wire 32 c t6 [31:0] $end
   $scope module alu $end
    $var wire  5 ) ALUCtrl_i [4:0] $end
    $var wire 32 T ALUResult_o [31:0] $end
    $var wire  3 R Flags_o [2:0] $end
    $var wire 32 e SrcA_i [31:0] $end
    $var wire 32 e SrcA_s [31:0] $end
    $var wire 32 S SrcB_i [31:0] $end
    $var wire 32 S SrcB_s [31:0] $end
   $upscope $end
   $scope module alu_mux $end
    $var wire 32 S ALUop_o [31:0] $end
    $var wire  1 d ALUsrc_i $end
    $var wire 32 * ImmOp_i [31:0] $end
    $var wire 32 f RegOp_i [31:0] $end
   $upscope $end
   $scope module control $end
    $var wire  5 ) ALUctrl_o [4:0] $end
    $var wire  1 d ALUsrc_o $end
    $var wire  3 R Flags_i [2:0] $end
    $var wire  3 ( ImmSrc_o [2:0] $end
    $var wire 32 $ Instr_i [31:0] $end
    $var wire  1 P MemWrite_o $end
    $var wire  2 Q PCsrc_o [1:0] $end
    $var wire  1 O RegWrite_o $end
    $var wire  2 & ResultSrc_o [1:0] $end
    $var wire  1 Y branch $end
    $var wire  3 ' funct3 [2:0] $end
    $var wire  1 / funct7 $end
    $var wire  1 W gt $end
    $var wire  1 X gtu $end
    $var wire  7 . op [6:0] $end
    $var wire  1 V zero $end
   $upscope $end
   $scope module dataMem $end
    $var wire 32 T a [31:0] $end
    $var wire  1 Z clk $end
    $var wire  3 ' funct3 [2:0] $end
    $var wire 32 \ ioin1 [31:0] $end
    $var wire 32 ] ioin2 [31:0] $end
    $var wire 32 U rd [31:0] $end
    $var wire 32 f wd [31:0] $end
    $var wire  1 P we $end
   $upscope $end
   $scope module extend $end
    $var wire 32 * ImmOp_o [31:0] $end
    $var wire  3 ( ImmSrc_i [2:0] $end
    $var wire 32 $ instr_i [31:0] $end
   $upscope $end
   $scope module instructions $end
    $var wire 32 # a [31:0] $end
    $var wire 32 $ rd [31:0] $end
   $upscope $end
   $scope module programCounter $end
    $var wire 32 T PCalu_i [31:0] $end
    $var wire  2 Q PCsrc_i [1:0] $end
    $var wire 32 % PCtarget_i [31:0] $end
    $var wire  1 Z clk $end
    $var wire 32 h next_PC [31:0] $end
    $var wire 32 # pc_o [31:0] $end
    $var wire  1 [ rst $end
   $upscope $end
   $scope module regfile $end
    $var wire  5 + AD1 [4:0] $end
    $var wire  5 , AD2 [4:0] $end
    $var wire  5 - AD3 [4:0] $end
    $var wire 32 e RD1 [31:0] $end
    $var wire 32 f RD2 [31:0] $end
    $var wire 32 g WD3 [31:0] $end
    $var wire  1 O WE3 $end
    $var wire 32 ^ a0 [31:0] $end
    $var wire 32 _ a1 [31:0] $end
    $var wire  1 Z clk $end
    $var wire 32 0 registers[0] [31:0] $end
    $var wire 32 : registers[10] [31:0] $end
    $var wire 32 ; registers[11] [31:0] $end
    $var wire 32 < registers[12] [31:0] $end
    $var wire 32 = registers[13] [31:0] $end
    $var wire 32 > registers[14] [31:0] $end
    $var wire 32 ? registers[15] [31:0] $end
    $var wire 32 @ registers[16] [31:0] $end
    $var wire 32 A registers[17] [31:0] $end
    $var wire 32 B registers[18] [31:0] $end
    $var wire 32 C registers[19] [31:0] $end
    $var wire 32 1 registers[1] [31:0] $end
    $var wire 32 D registers[20] [31:0] $end
    $var wire 32 E registers[21] [31:0] $end
    $var wire 32 F registers[22] [31:0] $end
    $var wire 32 G registers[23] [31:0] $end
    $var wire 32 H registers[24] [31:0] $end
    $var wire 32 I registers[25] [31:0] $end
    $var wire 32 J registers[26] [31:0] $end
    $var wire 32 K registers[27] [31:0] $end
    $var wire 32 L registers[28] [31:0] $end
    $var wire 32 M registers[29] [31:0] $end
    $var wire 32 2 registers[2] [31:0] $end
    $var wire 32 N registers[30] [31:0] $end
    $var wire 32 3 registers[3] [31:0] $end
    $var wire 32 4 registers[4] [31:0] $end
    $var wire 32 5 registers[5] [31:0] $end
    $var wire 32 6 registers[6] [31:0] $end
    $var wire 32 7 registers[7] [31:0] $end
    $var wire 32 8 registers[8] [31:0] $end
    $var wire 32 9 registers[9] [31:0] $end
    $var wire 32 ` t0 [31:0] $end
    $var wire 32 a t1 [31:0] $end
    $var wire 32 b t5 [31:0] $end
    $var wire 32 c t6 [31:0] $end
   $upscope $end
   $scope module result_mux $end
    $var wire 32 T ALU_i [31:0] $end
    $var wire 32 U Mem_i [31:0] $end
    $var wire 32 # PC_i [31:0] $end
    $var wire 32 % PCtarget_i [31:0] $end
    $var wire  2 & ResultSrc_i [1:0] $end
    $var wire 32 g Result_o [31:0] $end
   $upscope $end
   $scope module target $end
    $var wire 32 * ImmOp_i [31:0] $end
    $var wire 32 # PC_i [31:0] $end
    $var wire 32 % pcTarget_o [31:0] $end
   $upscope $end
  $upscope $end
 $upscope $end
$enddefinitions $end


#0
b00000000000000000000000000000000 #
b00000000000000000000000000000000 $
b00000000000000000000000000000000 %
b00 &
b000 '
b000 (
b00000 )
b00000000000000000000000000000000 *
b00000 +
b00000 ,
b00000 -
b0000000 .
0/
b00000000000000000000000000000000 0
b00000000000000000000000000000000 1
b00000000000000000000000000000000 2
b00000000000000000000000000000000 3
b00000000000000000000000000000000 4
b00000000000000000000000000000000 5
b00000000000000000000000000000000 6
b00000000000000000000000000000000 7
b00000000000000000000000000000000 8
b00000000000000000000000000000000 9
b00000000000000000000000000000000 :
b00000000000000000000000000000000 ;
b00000000000000000000000000000000 <
b00000000000000000000000000000000 =
b00000000000000000000000000000000 >
b00000000000000000000000000000000 ?
b00000000000000000000000000000000 @
b00000000000000000000000000000000 A
b00000000000000000000000000000000 B
b00000000000000000000000000000000 C
b00000000000000000000000000000000 D
b00000000000000000000000000000000 E
b00000000000000000000000000000000 F
b00000000000000000000000000000000 G
b00000000000000000000000000000000 H
b00000000000000000000000000000000 I
b00000000000000000000000000000000 J
b00000000000000000000000000000000 K
b00000000000000000000000000000000 L
b00000000000000000000000000000000 M
b00000000000000000000000000000000 N
0O
0P
b00 Q
b000 R
b00000000000000000000000000000000 S
b00000000000000000000000000000000 T
b00000000000000000000000000000000 U
0V
0W
0X
0Y
0Z
0[
b00000000000000000000000000000000 \
b00000000000000000000000000000000 ]
b00000000000000000000000000000000 ^
b00000000000000000000000000000000 _
b00000000000000000000000000000000 `
b00000000000000000000000000000000 a
b00000000000000000000000000000000 b
b00000000000000000000000000000000 c
0d
b00000000000000000000000000000000 e
b00000000000000000000000000000000 f
b00000000000000000000000000000000 g
b00000000000000000000000000000100 h
#1
b00000000000000000000010100010011 $
b01010 -
b0010011 .
1O
b111 R
1V
1W
1X
1Z
1d
#2
0Z
b00000000000000000000000000110011 ]
#3
b00000000000000000000000000000100 #
b00000111010000000000000011101111 $
b00000000000000000000000001111000 %
b10 &
b011 (
b00000000000000000000000001110100 *
b10100 ,
b00001 -
b1101111 .
b01 Q
1Z
0d
b00000000000000000000000000001000 g
b00000000000000000000000001111000 h
#4
b00000000000000000000000000001000 0
0Z
#5
b00000000000000000000000001111000 #
b00000000000100000000001010010011 $
b00000000000000000000000001111001 %
b00 &
b000 (
b00000000000000000000000000000001 *
b00001 ,
b00101 -
b0010011 .
b00 Q
b000 R
b00000000000000000000000000000001 S
b00000000000000000000000000000001 T
0V
0W
0X
1Z
1d
b00000000000000000000000000001000 f
b00000000000000000000000000000001 g
b00000000000000000000000001111100 h
#6
b00000000000000000000000000000001 4
0Z
b00000000000000000000000000000001 `
#7
b00000000000000000000000001111100 #
b00000000000100000000111110011011 $
b00000000000000000000000001111101 %
b11111 -
b0011011 .
0O
b00000000000000000000000000001000 S
b00000000000000000000000000001000 T
1Z
0d
b00000000000000000000000000001000 g
b00000000000000000000000010000000 h
#8
0Z
#9
b00000000000000000000000010000000 #
b00000010000011111001111110010011 $
b00000000000000000000000010100000 %
b001 '
b00011 )
b00000000000000000000000000100000 *
b11111 +
b00000 ,
b0010011 .
1O
b100 R
b00000000000000000000000000100000 S
b00000000000000000000000000000000 T
1V
1Z
1d
b00000000000000000000000000000000 f
b00000000000000000000000000000000 g
b00000000000000000000000010000100 h
#10
0Z
#11
b00000000000000000000000010000100 #
b11111111111111111000111110010011 $
b00000000000000000000000010000011 %
b000 '
b00000 )
b11111111111111111111111111111111 *
b11111 ,
1/
b010 R
b11111111111111111111111111111111 S
b11111111111111111111111111111111 T
0V
1W
1Z
b11111111111111111111111111111111 g
b00000000000000000000000010001000 h
#12
b11111111111111111111111111111111 N
b011 R
b11111111111111111111111111111110 T
b00000000000000000000000000110011 U
1X
0Z
b11111111111111111111111111111111 c
b11111111111111111111111111111111 e
b11111111111111111111111111111111 f
b11111111111111111111111111111110 g
#13
b00000000000000000000000010001000 #
b00000000000000101000001100010011 $
b00000000000000000000000010001000 %
b00000000000000000000000000000000 *
b00101 +
b00000 ,
b00110 -
0/
b00000000000000000000000000000000 S
b00000000000000000000000000000001 T
b00000000000000000000000000000000 U
1Z
b00000000000000000000000000000001 e
b00000000000000000000000000000000 f
b00000000000000000000000000000001 g
b00000000000000000000000010001100 h
#14
b00000000000000000000000000000001 5
0Z
b00000000000000000000000000000001 a
#15
b00000000000000000000000010001100 #
b00000000010000110111001110010011 $
b00000000000000000000000010010000 %
b111 '
b01100 )
b00000000000000000000000000000100 *
b00110 +
b00100 ,
b00111 -
b100 R
b00000000000000000000000000000100 S
b00000000000000000000000000000000 T
1V
0W
0X
1Z
b00000000000000000000000000000000 g
b00000000000000000000000010010000 h
#16
0Z
#17
b00000000000000000000000010010000 #
b00000100000000110111111000010011 $
b00000000000000000000000011010000 %
b00000000000000000000000001000000 *
b00000 ,
b11100 -
b00000000000000000000000001000000 S
1Z
b00000000000000000000000010010100 h
#18
0Z
#19
b00000000000000000000000010010100 #
b00000000001000111101001110010011 $
b00000000000000000000000010010110 %
b101 '
b01001 )
b00000000000000000000000000000010 *
b00111 +
b00010 ,
b00111 -
b00000000000000000000000000000010 S
1Z
b00000000000000000000000000000000 e
b00000000000000000000000010011000 h
#20
0Z
#21
b00000000000000000000000010011000 #
b00000000011011100101111000010011 $
b00000000000000000000000010011110 %
b00000000000000000000000000000110 *
b11100 +
b00110 ,
b11100 -
b00000000000000000000000000000110 S
1Z
b00000000000000000000000000000001 f
b00000000000000000000000010011100 h
#22
0Z
#23
b00000000000000000000000010011100 #
b00000001110000111100111010110011 $
b00000000000000000000000010111000 %
b100 '
b00110 )
b00000000000000000000000000011100 *
b00111 +
b11100 ,
b11101 -
b0110011 .
b111 R
b00000000000000000000000000000000 S
1W
1X
1Z
0d
b00000000000000000000000000000000 f
b00000000000000000000000010100000 h
#24
0Z
#25
b00000000000000000000000010100000 #
b00000000000100101001001010010011 $
b00000000000000000000000010100001 %
b001 '
b00011 )
b00000000000000000000000000000001 *
b00101 +
b00001 ,
b00101 -
b0010011 .
b011 R
b00000000000000000000000000000001 S
b00000000000000000000000000000010 T
0V
1Z
1d
b00000000000000000000000000000001 e
b00000000000000000000000000001000 f
b00000000000000000000000000000010 g
b00000000000000000000000010100100 h
#26
b00000000000000000000000000000010 4
b00000000000000000000000000000100 T
0Z
b00000000000000000000000000000010 `
b00000000000000000000000000000010 e
b00000000000000000000000000000100 g
#27
b00000000000000000000000010100100 #
b00000001110100101000001010110011 $
b00000000000000000000000011000001 %
b000 '
b00000 )
b00000000000000000000000000011101 *
b11101 ,
b0110011 .
b00000000000000000000000000000000 S
b00000000000000000000000000000010 T
1Z
0d
b00000000000000000000000000000000 f
b00000000000000000000000000000010 g
b00000000000000000000000010101000 h
#28
0Z
#29
b00000000000000000000000010101000 #
b00001111111100101111001010010011 $
b00000000000000000000000110100111 %
b111 '
b01100 )
b00000000000000000000000011111111 *
b11111 ,
b0010011 .
b000 R
b00000000000000000000000011111111 S
0W
0X
1Z
1d
b11111111111111111111111111111111 f
b00000000000000000000000010101100 h
#30
0Z
#31
b00000000000000000000000010101100 #
b00000000000011111010111100000011 $
b00000000000000000000000010101100 %
b01 &
b010 '
b00000 )
b00000000000000000000000000000000 *
b11111 +
b00000 ,
b11110 -
b0000011 .
b001 R
b00000000000000000000000000000000 S
b11111111111111111111111111111111 T
1X
1Z
b11111111111111111111111111111111 e
b00000000000000000000000000000000 f
b00000000000000000000000000000000 g
b00000000000000000000000010110000 h
#32
0Z
#33
b00000000000000000000000010110000 #
b11111100000011110000110011100011 $
b00000000000000000000000010001000 %
b00 &
b000 '
b010 (
b00001 )
b11111111111111111111111111011000 *
b11110 +
b11001 -
b1100011 .
1/
0O
b01 Q
b111 R
b00000000000000000000000000000000 T
1V
1W
1Y
1Z
0d
b00000000000000000000000000000000 e
b00000000000000000000000010001000 h
#34
0Z
#35
b00000000000000000000000010001000 #
b00000000000000101000001100010011 $
b000 (
b00000 )
b00000000000000000000000000000000 *
b00101 +
b00110 -
b0010011 .
0/
1O
b00 Q
b011 R
b00000000000000000000000000000010 T
0V
0Y
1Z
1d
b00000000000000000000000000000010 e
b00000000000000000000000000000010 g
b00000000000000000000000010001100 h
#36
b00000000000000000000000000000010 5
0Z
b00000000000000000000000000000010 a
#37
b00000000000000000000000010001100 #
b00000000010000110111001110010011 $
b00000000000000000000000010010000 %
b111 '
b01100 )
b00000000000000000000000000000100 *
b00110 +
b00100 ,
b00111 -
b100 R
b00000000000000000000000000000100 S
b00000000000000000000000000000000 T
1V
0W
0X
1Z
b00000000000000000000000000000000 g
b00000000000000000000000010010000 h
#38
0Z
#39
b00000000000000000000000010010000 #
b00000100000000110111111000010011 $
b00000000000000000000000011010000 %
b00000000000000000000000001000000 *
b00000 ,
b11100 -
b00000000000000000000000001000000 S
1Z
b00000000000000000000000010010100 h
#40
0Z
#41
b00000000000000000000000010010100 #
b00000000001000111101001110010011 $
b00000000000000000000000010010110 %
b101 '
b01001 )
b00000000000000000000000000000010 *
b00111 +
b00010 ,
b00111 -
b00000000000000000000000000000010 S
1Z
b00000000000000000000000000000000 e
b00000000000000000000000010011000 h
#42
0Z
#43
b00000000000000000000000010011000 #
b00000000011011100101111000010011 $
b00000000000000000000000010011110 %
b00000000000000000000000000000110 *
b11100 +
b00110 ,
b11100 -
b00000000000000000000000000000110 S
1Z
b00000000000000000000000000000010 f
b00000000000000000000000010011100 h
#44
0Z
#45
b00000000000000000000000010011100 #
b00000001110000111100111010110011 $
b00000000000000000000000010111000 %
b100 '
b00110 )
b00000000000000000000000000011100 *
b00111 +
b11100 ,
b11101 -
b0110011 .
b111 R
b00000000000000000000000000000000 S
1W
1X
1Z
0d
b00000000000000000000000000000000 f
b00000000000000000000000010100000 h
#46
0Z
#47
b00000000000000000000000010100000 #
b00000000000100101001001010010011 $
b00000000000000000000000010100001 %
b001 '
b00011 )
b00000000000000000000000000000001 *
b00101 +
b00001 ,
b00101 -
b0010011 .
b011 R
b00000000000000000000000000000001 S
b00000000000000000000000000000100 T
0V
1Z
1d
b00000000000000000000000000000010 e
b00000000000000000000000000001000 f
b00000000000000000000000000000100 g
b00000000000000000000000010100100 h
#48
b00000000000000000000000000000100 4
b00000000000000000000000000001000 T
0Z
b00000000000000000000000000000100 `
b00000000000000000000000000000100 e
b00000000000000000000000000001000 g
#49
b00000000000000000000000010100100 #
b00000001110100101000001010110011 $
b00000000000000000000000011000001 %
b000 '
b00000 )
b00000000000000000000000000011101 *
b11101 ,
b0110011 .
b00000000000000000000000000000000 S
b00000000000000000000000000000100 T
1Z
0d
b00000000000000000000000000000000 f
b00000000000000000000000000000100 g
b00000000000000000000000010101000 h
#50
0Z
