rtl/Resultmux.sv
module Resultmux(
    input [31:0] ALU_i,
    input [31:0] Mem_i,
    input [31:0] PC_i,
    input [1:0] ResultSrc_i,
    output reg [31:0] Result_o
);

always_comb begin
    
    case(ResultSrc_i)

    0: Result_o = ALU_i;
    1: Result_o = Mem_i;
    2: Result_o = PC_i;

    default: Result_o = ALU_i;
    
    endcase

end

endmodule

rtl/DataMem.sv
module DataMem(
    input clk,
    input [31:0] a,
    input  [31:0] wd,
    //input [1:0] size, //byte, half, word
    input we,
    output reg [31:0] rd
);

//how can we implement byte-addressable memory?
//top 30 bits are addressing the word
//bottom 2 bits are addressing the byte

bit [31:0] Memory [bit[31:0]]; //2^32 -1

//logic [31:0] Memory [29:0];
//logic [29:0] word;
//logic [1:0] byte; //byte is not allowed as var name
//assign {word, byte} = a;

always_ff@(posedge clk)
    if(we) Memory[a] <= wd;
    else rd <= Memory[a];

endmodule

rtl/PCTarget.sv
module PCTarget(
    input [31:0] ImmOp_i,
    input [31:0] PC_i,
    output [31:0] pcTarget_o
);

assign pcTarget_o = PC_i + ImmOp_i;

endmodule

rtl/ALU.sv
module ALU (
    input [4:0] ALUCtrl_i, //we got 13 cases
    input [31:0] SrcA_i,
    input [31:0] SrcB_i,
    output reg [31:0] ALUResult_o,
    output [2:0] Flags_o 
);

/////////// Flags for Branches /////////////////////////

logic zero; logic gt; logic gtu; // zero, greater-than, greater-than-unsigned
logic signed [31:0] SrcA_s; logic signed [31:0] SrcB_s; 

assign SrcA_s = SrcA_i;
assign SrcB_s = SrcB_i;
assign zero = (ALUResult_o == 0);
assign gt = (SrcA_s >= SrcB_s);
assign gtu = (SrcA_i >= SrcB_i);

assign Flags_o = {zero, gt, gtu};

////////////// Instructions ////////////////////////

always_comb begin
    case(ALUCtrl_i)
    0: ALUResult_o = SrcA_s + SrcB_s; //add
    1: ALUResult_o = SrcA_s - SrcB_s; //sub
    2: ALUResult_o = SrcA_s << SrcB_s[4:0]; //SLL reg
    3: ALUResult_o = SrcA_s << SrcB_s; // SLL imm
    4: ALUResult_o = {{31{1'b0}},(SrcA_s < SrcB_s)};  //SLT
    5: ALUResult_o = {{31{1'b0}}, (SrcA_i < SrcB_i)}; // SLT unsigned
    6: ALUResult_o = SrcA_s ^ SrcB_s; // xor
    7: ALUResult_o = SrcA_s >> SrcB_s[4:0]; // SRL reg
    8: ALUResult_o = SrcA_s >>> SrcB_s[4:0]; // SRA reg
    9: ALUResult_o = SrcA_s >> SrcB_s; // SRL imm
    10: ALUResult_o = SrcA_s >>> SrcB_s; // SRA imm
    11: ALUResult_o = SrcA_s | SrcB_s; // or
    12: ALUResult_o = SrcA_s & SrcB_s; // and 
    default: ALUResult_o = SrcA_s + SrcB_s;

    endcase

end


endmodule

rtl/ALUmux.sv
module ALUmux(
    input [31:0] RegOp_i,
    input [31:0] ImmOp_i,
    input ALUsrc_i,
    output reg [31:0] ALUop_o
);

always_comb begin
    if(ALUsrc_i) ALUop_o = ImmOp_i;
    else ALUop_o = RegOp_i;
end 

endmodule

rtl/SignExtend.sv
module SignExtend(
    input [31:0] instr_i,
    input [1:0] ImmSrc_i,
    output reg [31:0] ImmOp_o
);

always_comb begin

    case(ImmSrc_i)
    
    0: ImmOp_o = {{20{instr_i[31]}}, instr_i[31:20]}; // i-type
    1:ImmOp_o = {{20{instr_i[31]}}, instr_i[31:25], instr_i[11:7]}; //s-type
    2: ImmOp_o = {{20{instr_i[31]}}, instr_i[7], instr_i[30:25], instr_i[11:8], 1'b0}; //b-type
    3: ImmOp_o = {{12{instr_i[31]}}, instr_i[19:12], instr_i[20], instr_i[30:21], 1'b0}; // j-type
    
    default: ImmOp_o = 0;

    endcase 

end

endmodule

rtl/RegFile.sv
module RegFile(
    input clk,
    input [4:0] AD1,
    input [4:0] AD2,
    input [4:0] AD3,
    input WE3,
    input [31:0] WD3,
    output reg [31:0] RD1,
    output reg [31:0] RD2,
    output [31:0] a0 
);

//logic [31:0] registers [6:0];

bit [31:0] registers[31];

assign a0 = registers[10];

always_ff @(posedge clk) begin
    if(WE3) registers[AD3] <= WD3;
end

always_ff @(negedge clk) begin
RD1 <= registers[AD1];
RD2 <= registers[AD2]; 
end

endmodule

rtl/ControlUnit.sv
module ControlUnit(
    input [2:0] Flags_i, //flags
    input [31:0] Instr_i, 
    output reg RegWrite_o, //register write enable
    output reg ALUsrc_o, //use imm or RD2
    output reg MemWrite_o, // memory write enable
    output reg [1:0] ImmSrc_o, //determine imm-type
    output reg [4:0] ALUctrl_o, //determine alu-op
    output reg PCsrc_o, // PC+4 or PC+imm
    output reg [1:0] ResultSrc_o // ALU result, Data memory, PC+4
);

///////////// Internal Signals /////////////////////////////

logic [6:0] op; logic [2:0] funct3; logic funct7; //opcodes
logic zero; logic gt; logic gtu; //flags
logic branch; logic jump; // branch, jump

assign {op, funct3, funct7} = {Instr_i[6:0], Instr_i[14:12], Instr_i[30]}; 
assign {zero, gt, gtu} = Flags_i;

///////////// RegWrite, ALUSrc, Memwrite, PCSrc ////////////////////////

always_comb begin
    RegWrite_o = (op == 3) || (op == 19) || (op == 51) || (op == 55) || (op == 103) || (op == 111); //all except s-type
    ALUsrc_o = (op == 3) || (op==19) || (op==35) || (op==55) || (op==103); //all except r-type and b-type
    MemWrite_o = (op == 35); // s-type
    PCsrc_o = branch | jump; 
end

always_comb begin

    case(op)

        ////////////////// r-type and i-type  ////////////////
        51, 19: begin  
            ResultSrc_o = 0; // ALU result
            ImmSrc_o = 0; // for i-type
            branch = 0;
            jump = 0;
            
            if(op[5]) ALUsrc_o = 0; //rd2
            else ALUsrc_o = 1; //imm

            case(funct3)
            0: begin
                if(op[5]) begin 
                    if(funct7 == 0) ALUctrl_o = 0;
                    else ALUctrl_o = 1;
                end
                else ALUctrl_o = 0;
                end
            1: begin if(op[5]) ALUctrl_o = 2;
                    else ALUctrl_o = 3;
                end 
            2: ALUctrl_o = 4;
            3: ALUctrl_o = 5;
            4: ALUctrl_o = 6;
            5: begin 
                if(op[5]) begin
                    if(funct7 == 0) ALUctrl_o = 7;
                    else ALUctrl_o = 8;
                end
                else begin 
                    if(funct7 == 0) ALUctrl_o = 9;
                    else ALUctrl_o = 10;
                end
            end 
            6: ALUctrl_o = 11;
            7: ALUctrl_o = 12;

            default: ALUctrl_o = 0;
            endcase
        end

        /////////////////// b-type ///////////////////////

        99: begin
            
            ALUsrc_o = 0; //reg
            ALUctrl_o = 1; //x cause flags
            ImmSrc_o = 2; // 13-bit immediate
            ResultSrc_o = 0; //x
            jump = 0;

            case(funct3)

            0: begin ///////////////beq
                if(zero) branch = 0;
                else branch = 1;
            end
            1: begin ///////////////bne
                if(~zero) branch = 1;
                else branch = 0;
            end
            4: begin //////////////blt
                if(~gt) branch = 1;
                else branch = 0;
            end
            5: begin ///////////////bge
                if(gt) branch = 1;
                else branch = 0;
            end
            6:begin ////////////////bltu
                if(~gtu) branch = 1;
                else branch = 0;
            end
            7:begin /////////////// bgtu
                if(gtu) branch = 1;
                else branch = 0;
            end

            endcase

        end


        ////////////////////////  s-type /////////////////

        35: begin //sw only
        ImmSrc_o = 1;
        ALUsrc_o = 1; //imm
        ALUctrl_o = 0; //add
        ResultSrc_o = 0; //x 
        branch = 0; //x
        jump = 0; //x
        end


        /////////////////////// l-type //////////////////

        3: begin //lw only
        ImmSrc_o = 0;
        ALUsrc_o = 1;
        ALUctrl_o = 0; //add
        ResultSrc_o = 1;
        branch = 0;
        jump = 0;
        end


        ////// u-type, jal, jalr /////////////

    endcase

end 


endmodule

rtl/InstrMem.sv
module InstrMem(
    input [31:0] a,
    output [31:0] rd 
);

bit [31:0] ram_array [bit[31:0]]; //2^32 -1

initial begin
    $display("Loading program.");
    $readmemh("counter.mem", ram_array);
end

assign rd = ram_array[a];

endmodule

rtl/PC.sv
module PC(
    input clk,
    input rst,
    input PCsrc_i,
    input [31:0] pcTarget_i,
    output reg [31:0] pc_o
);

//assuming we need 32 bits for instr mem addresses
logic [31:0] next_PC;

always_ff @(posedge clk) begin
    if(rst) pc_o <= 0;
    else pc_o <= next_PC;
end

always_comb begin
    if(PCsrc_i) next_PC = pcTarget_i;
    else next_PC = pc_o + 4;
end 

endmodule

rtl/CPU.sv
module CPU(
    input clk,
    input rst,
    output [31:0] a0
);

//////////// fetch ///////////////

// Signals for PC
logic [31:0] pc, instr, pcTarget;

PC programCounter (.clk(clk), .rst(rst), .PCsrc_i(pcsrc), 
.pcTarget_i(pcTarget), .pc_o(pc)); //careful about pipelining PCTarget

// Fetch instruction
InstrMem instructions(.a(pc), .rd(instr));

//////////// Decode //////////////

//Signals for control unit
logic alusrc, regwrite, memwrite, pcsrc;
logic [1:0] immsrc, resultsrc;
logic [2:0] flags;
logic [4:0] aluctrl;

ControlUnit control(.Flags_i(flags), .Instr_i(instr), 
.RegWrite_o(regwrite), .ALUsrc_o(alusrc), .ALUctrl_o(aluctrl), .ImmSrc_o(immsrc), 
.MemWrite_o(memwrite), .ResultSrc_o(resultsrc), .PCsrc_o(pcsrc));

// Register file signals
logic [31:0] rd1, rd2, imm_op;
logic [4:0] rs1, rs2, rd;
assign rs1 = instr[19:15];
assign rs2 = instr[24:20];
assign rd = instr[11:7];

// Instantiate Register File
RegFile regfile(.clk(clk), .AD1(rs1), .AD2(rs2), 
    .AD3(rd), .WE3(regwrite), .WD3(result), .RD1(rd1), //wd3
    .RD2(rd2), .a0(a0));

SignExtend extend( .instr_i(instr), .ImmSrc_i(immsrc), .ImmOp_o(imm_op));

//////////// Execute ///////////////

// ALU signals
logic [31:0] src_b, alu_result;

ALUmux alu_mux(.RegOp_i(rd2), .ImmOp_i(imm_op), .ALUsrc_i(alusrc), .ALUop_o(src_b));

ALU alu(.ALUCtrl_i(aluctrl), .SrcA_i(rd1), .SrcB_i(src_b), .ALUResult_o(alu_result),
 .Flags_o(flags));

PCTarget target(.ImmOp_i(imm_op), .PC_i(pc), .pcTarget_o(pcTarget));

/////////// Memory //////////////

// Memory signals
logic [31:0] mem_data;

DataMem dataMem(.clk(clk), .a(alu_result), .wd(rd2), .we(memwrite), .rd(mem_data));

/////////// Writeback //////////////
logic [31:0] result;

Resultmux result_mux( .ALU_i(alu_result), .Mem_i(mem_data), .PC_i(pc),
    .ResultSrc_i(resultsrc),
    .Result_o(result));

endmodule

rtl/CPU.vcd
$version Generated by VerilatedVcd $end
$date Fri Jul 19 13:32:10 2024 $end
$timescale 1ps $end

 $scope module TOP $end
  $var wire 32 ^ a0 [31:0] $end
  $var wire  1 \ clk $end
  $var wire  1 ] rst $end
  $scope module CPU $end
   $var wire 32 ^ a0 [31:0] $end
   $var wire 32 V alu_result [31:0] $end
   $var wire  5 + aluctrl [4:0] $end
   $var wire  1 & alusrc $end
   $var wire  1 \ clk $end
   $var wire  3 T flags [2:0] $end
   $var wire 32 , imm_op [31:0] $end
   $var wire  2 ) immsrc [1:0] $end
   $var wire 32 $ instr [31:0] $end
   $var wire 32 0 mem_data [31:0] $end
   $var wire  1 ( memwrite $end
   $var wire 32 # pc [31:0] $end
   $var wire 32 % pcTarget [31:0] $end
   $var wire  1 _ pcsrc $end
   $var wire  5 / rd [4:0] $end
   $var wire 32 ` rd1 [31:0] $end
   $var wire 32 a rd2 [31:0] $end
   $var wire  1 ' regwrite $end
   $var wire 32 b result [31:0] $end
   $var wire  2 * resultsrc [1:0] $end
   $var wire  5 - rs1 [4:0] $end
   $var wire  5 . rs2 [4:0] $end
   $var wire  1 ] rst $end
   $var wire 32 U src_b [31:0] $end
   $scope module alu $end
    $var wire  5 + ALUCtrl_i [4:0] $end
    $var wire 32 V ALUResult_o [31:0] $end
    $var wire  3 T Flags_o [2:0] $end
    $var wire 32 ` SrcA_i [31:0] $end
    $var wire 32 ` SrcA_s [31:0] $end
    $var wire 32 U SrcB_i [31:0] $end
    $var wire 32 U SrcB_s [31:0] $end
    $var wire  1 c gt $end
    $var wire  1 d gtu $end
    $var wire  1 W zero $end
   $upscope $end
   $scope module alu_mux $end
    $var wire 32 U ALUop_o [31:0] $end
    $var wire  1 & ALUsrc_i $end
    $var wire 32 , ImmOp_i [31:0] $end
    $var wire 32 a RegOp_i [31:0] $end
   $upscope $end
   $scope module control $end
    $var wire  5 + ALUctrl_o [4:0] $end
    $var wire  1 & ALUsrc_o $end
    $var wire  3 T Flags_i [2:0] $end
    $var wire  2 ) ImmSrc_o [1:0] $end
    $var wire 32 $ Instr_i [31:0] $end
    $var wire  1 ( MemWrite_o $end
    $var wire  1 _ PCsrc_o $end
    $var wire  1 ' RegWrite_o $end
    $var wire  2 * ResultSrc_o [1:0] $end
    $var wire  1 [ branch $end
    $var wire  3 2 funct3 [2:0] $end
    $var wire  1 3 funct7 $end
    $var wire  1 Y gt $end
    $var wire  1 Z gtu $end
    $var wire  1 4 jump $end
    $var wire  7 1 op [6:0] $end
    $var wire  1 X zero $end
   $upscope $end
   $scope module dataMem $end
    $var wire 32 V a [31:0] $end
    $var wire  1 \ clk $end
    $var wire 32 0 rd [31:0] $end
    $var wire 32 a wd [31:0] $end
    $var wire  1 ( we $end
   $upscope $end
   $scope module extend $end
    $var wire 32 , ImmOp_o [31:0] $end
    $var wire  2 ) ImmSrc_i [1:0] $end
    $var wire 32 $ instr_i [31:0] $end
   $upscope $end
   $scope module instructions $end
    $var wire 32 # a [31:0] $end
    $var wire 32 $ rd [31:0] $end
   $upscope $end
   $scope module programCounter $end
    $var wire  1 _ PCsrc_i $end
    $var wire  1 \ clk $end
    $var wire 32 e next_PC [31:0] $end
    $var wire 32 % pcTarget_i [31:0] $end
    $var wire 32 # pc_o [31:0] $end
    $var wire  1 ] rst $end
   $upscope $end
   $scope module regfile $end
    $var wire  5 - AD1 [4:0] $end
    $var wire  5 . AD2 [4:0] $end
    $var wire  5 / AD3 [4:0] $end
    $var wire 32 ` RD1 [31:0] $end
    $var wire 32 a RD2 [31:0] $end
    $var wire 32 b WD3 [31:0] $end
    $var wire  1 ' WE3 $end
    $var wire 32 ^ a0 [31:0] $end
    $var wire  1 \ clk $end
    $var wire 32 5 registers[0] [31:0] $end
    $var wire 32 ? registers[10] [31:0] $end
    $var wire 32 @ registers[11] [31:0] $end
    $var wire 32 A registers[12] [31:0] $end
    $var wire 32 B registers[13] [31:0] $end
    $var wire 32 C registers[14] [31:0] $end
    $var wire 32 D registers[15] [31:0] $end
    $var wire 32 E registers[16] [31:0] $end
    $var wire 32 F registers[17] [31:0] $end
    $var wire 32 G registers[18] [31:0] $end
    $var wire 32 H registers[19] [31:0] $end
    $var wire 32 6 registers[1] [31:0] $end
    $var wire 32 I registers[20] [31:0] $end
    $var wire 32 J registers[21] [31:0] $end
    $var wire 32 K registers[22] [31:0] $end
    $var wire 32 L registers[23] [31:0] $end
    $var wire 32 M registers[24] [31:0] $end
    $var wire 32 N registers[25] [31:0] $end
    $var wire 32 O registers[26] [31:0] $end
    $var wire 32 P registers[27] [31:0] $end
    $var wire 32 Q registers[28] [31:0] $end
    $var wire 32 R registers[29] [31:0] $end
    $var wire 32 7 registers[2] [31:0] $end
    $var wire 32 S registers[30] [31:0] $end
    $var wire 32 8 registers[3] [31:0] $end
    $var wire 32 9 registers[4] [31:0] $end
    $var wire 32 : registers[5] [31:0] $end
    $var wire 32 ; registers[6] [31:0] $end
    $var wire 32 < registers[7] [31:0] $end
    $var wire 32 = registers[8] [31:0] $end
    $var wire 32 > registers[9] [31:0] $end
   $upscope $end
   $scope module result_mux $end
    $var wire 32 V ALU_i [31:0] $end
    $var wire 32 0 Mem_i [31:0] $end
    $var wire 32 # PC_i [31:0] $end
    $var wire  2 * ResultSrc_i [1:0] $end
    $var wire 32 b Result_o [31:0] $end
   $upscope $end
   $scope module target $end
    $var wire 32 , ImmOp_i [31:0] $end
    $var wire 32 # PC_i [31:0] $end
    $var wire 32 % pcTarget_o [31:0] $end
   $upscope $end
  $upscope $end
 $upscope $end
$enddefinitions $end


#0
b00000000000000000000000000000000 #
b00000000000000000000000000000000 $
b00000000000000000000000000000000 %
0&
0'
0(
b00 )
b00 *
b00000 +
b00000000000000000000000000000000 ,
b00000 -
b00000 .
b00000 /
b00000000000000000000000000000000 0
b0000000 1
b000 2
03
04
b00000000000000000000000000000000 5
b00000000000000000000000000000000 6
b00000000000000000000000000000000 7
b00000000000000000000000000000000 8
b00000000000000000000000000000000 9
b00000000000000000000000000000000 :
b00000000000000000000000000000000 ;
b00000000000000000000000000000000 <
b00000000000000000000000000000000 =
b00000000000000000000000000000000 >
b00000000000000000000000000000000 ?
b00000000000000000000000000000000 @
b00000000000000000000000000000000 A
b00000000000000000000000000000000 B
b00000000000000000000000000000000 C
b00000000000000000000000000000000 D
b00000000000000000000000000000000 E
b00000000000000000000000000000000 F
b00000000000000000000000000000000 G
b00000000000000000000000000000000 H
b00000000000000000000000000000000 I
b00000000000000000000000000000000 J
b00000000000000000000000000000000 K
b00000000000000000000000000000000 L
b00000000000000000000000000000000 M
b00000000000000000000000000000000 N
b00000000000000000000000000000000 O
b00000000000000000000000000000000 P
b00000000000000000000000000000000 Q
b00000000000000000000000000000000 R
b00000000000000000000000000000000 S
b000 T
b00000000000000000000000000000000 U
b00000000000000000000000000000000 V
1W
0X
0Y
0Z
0[
1\
0]
b00000000000000000000000000000000 ^
0_
b00000000000000000000000000000000 `
b00000000000000000000000000000000 a
b00000000000000000000000000000000 b
1c
1d
b00000000000000000000000000000100 e
#1
b00001111111100000000001100010011 $
b00000000000000000000000011111111 %
1&
1'
b00000000000000000000000011111111 ,
b11111 .
b00110 /
b0010011 1
b00000000000000000000000011111111 U
b00000000000000000000000011111111 V
0W
0\
b00000000000000000000000011111111 b
0c
0d
#2
b00000000000000000000000000000100 #
b00000000000101011000010110010011 $
b00000000000000000000000000000101 %
b00000000000000000000000000000001 ,
b01011 -
b00001 .
b01011 /
b00000000000000000000000011111111 ;
b00000000000000000000000000000001 U
b00000000000000000000000000000001 V
1\
b00000000000000000000000000000001 b
b00000000000000000000000000001000 e
#3
0\
#4
b00000000000000000000000000001000 #
b00000000000000000000000000000000 $
b00000000000000000000000000001000 %
0&
0'
b00000000000000000000000000000000 ,
b00000 -
b00000 .
b00000 /
b0000000 1
b00000000000000000000000000000001 @
b111 T
b00000000000000000000000000000000 U
b00000000000000000000000000000000 V
1W
1X
1Y
1Z
1\
b00000000000000000000000000000000 b
1c
1d
b00000000000000000000000000001100 e
#5
0\
#6
b00000000000000000000000000001100 #
b00000000000000000000000000001100 %
1\
b00000000000000000000000000010000 e
#7
0\
#8
b00000000000000000000000000010000 #
b00000000000000000000000000010000 %
1\
b00000000000000000000000000010100 e
#9
0\
#10
b00000000000000000000000000010100 #
b00000000000000000000000000010100 %
1\
b00000000000000000000000000011000 e
#11
0\
#12
b00000000000000000000000000011000 #
b00000000000000000000000000011000 %
1\
b00000000000000000000000000011100 e
#13
0\
#14
b00000000000000000000000000011100 #
b00000000000000000000000000011100 %
1\
b00000000000000000000000000100000 e
#15
0\
#16
b00000000000000000000000000100000 #
b00000000000000000000000000100000 %
1\
b00000000000000000000000000100100 e
#17
0\
#18
b00000000000000000000000000100100 #
b00000000000000000000000000100100 %
1\
b00000000000000000000000000101000 e
#19
0\
#20
b00000000000000000000000000101000 #
b00000000000000000000000000101000 %
1\
b00000000000000000000000000101100 e
#21
0\
#22
b00000000000000000000000000101100 #
b00000000000000000000000000101100 %
1\
b00000000000000000000000000110000 e
#23
0\
#24
b00000000000000000000000000110000 #
b00000000000000000000000000110000 %
1\
b00000000000000000000000000110100 e
#25
0\
#26
b00000000000000000000000000110100 #
b00000000000000000000000000110100 %
1\
b00000000000000000000000000111000 e
#27
0\
#28
b00000000000000000000000000111000 #
b00000000000000000000000000111000 %
1\
b00000000000000000000000000111100 e
#29
0\
#30
b00000000000000000000000000111100 #
b00000000000000000000000000111100 %
1\
b00000000000000000000000001000000 e
#31
0\
#32
b00000000000000000000000001000000 #
b00000000000000000000000001000000 %
1\
b00000000000000000000000001000100 e
#33
0\
#34
b00000000000000000000000001000100 #
b00000000000000000000000001000100 %
1\
b00000000000000000000000001001000 e
#35
0\
#36
b00000000000000000000000001001000 #
b00000000000000000000000001001000 %
1\
b00000000000000000000000001001100 e
#37
0\
#38
b00000000000000000000000001001100 #
b00000000000000000000000001001100 %
1\
b00000000000000000000000001010000 e
#39
0\
#40
b00000000000000000000000001010000 #
b00000000000000000000000001010000 %
1\
b00000000000000000000000001010100 e
#41
0\
#42
b00000000000000000000000001010100 #
b00000000000000000000000001010100 %
1\
b00000000000000000000000001011000 e
#43
0\
#44
b00000000000000000000000001011000 #
b00000000000000000000000001011000 %
1\
b00000000000000000000000001011100 e
#45
0\
#46
b00000000000000000000000001011100 #
b00000000000000000000000001011100 %
1\
b00000000000000000000000001100000 e
#47
0\
#48
b00000000000000000000000001100000 #
b00000000000000000000000001100000 %
1\
b00000000000000000000000001100100 e
#49
0\
#50
b00000000000000000000000001100100 #
b00000000000000000000000001100100 %
1\
b00000000000000000000000001101000 e
#51
0\
#52
b00000000000000000000000001101000 #
b00000000000000000000000001101000 %
1\
b00000000000000000000000001101100 e
#53
0\
#54
b00000000000000000000000001101100 #
b00000000000000000000000001101100 %
1\
b00000000000000000000000001110000 e
#55
0\
#56
b00000000000000000000000001110000 #
b00000000000000000000000001110000 %
1\
b00000000000000000000000001110100 e
#57
0\
#58
b00000000000000000000000001110100 #
b00000000000000000000000001110100 %
1\
b00000000000000000000000001111000 e
#59
0\
#60
b00000000000000000000000001111000 #
b00000000000000000000000001111000 %
1\
b00000000000000000000000001111100 e
#61
0\
#62
b00000000000000000000000001111100 #
b00000000000000000000000001111100 %
1\
b00000000000000000000000010000000 e
#63
0\
#64
b00000000000000000000000010000000 #
b00000000000000000000000010000000 %
1\
b00000000000000000000000010000100 e
#65
0\
#66
b00000000000000000000000010000100 #
b00000000000000000000000010000100 %
1\
b00000000000000000000000010001000 e
#67
0\
#68
b00000000000000000000000010001000 #
b00000000000000000000000010001000 %
1\
b00000000000000000000000010001100 e
#69
0\
#70
b00000000000000000000000010001100 #
b00000000000000000000000010001100 %
1\
b00000000000000000000000010010000 e
#71
0\
#72
b00000000000000000000000010010000 #
b00000000000000000000000010010000 %
1\
b00000000000000000000000010010100 e
#73
0\
#74
b00000000000000000000000010010100 #
b00000000000000000000000010010100 %
1\
b00000000000000000000000010011000 e
#75
0\
#76
b00000000000000000000000010011000 #
b00000000000000000000000010011000 %
1\
b00000000000000000000000010011100 e
#77
0\
#78
b00000000000000000000000010011100 #
b00000000000000000000000010011100 %
1\
b00000000000000000000000010100000 e
#79
0\
#80
b00000000000000000000000010100000 #
b00000000000000000000000010100000 %
1\
b00000000000000000000000010100100 e
#81
0\
#82
b00000000000000000000000010100100 #
b00000000000000000000000010100100 %
1\
b00000000000000000000000010101000 e
#83
0\
#84
b00000000000000000000000010101000 #
b00000000000000000000000010101000 %
1\
b00000000000000000000000010101100 e
#85
0\
#86
b00000000000000000000000010101100 #
b00000000000000000000000010101100 %
1\
b00000000000000000000000010110000 e
#87
0\
#88
b00000000000000000000000010110000 #
b00000000000000000000000010110000 %
1\
b00000000000000000000000010110100 e
#89
0\
#90
b00000000000000000000000010110100 #
b00000000000000000000000010110100 %
1\
b00000000000000000000000010111000 e
#91
0\
#92
b00000000000000000000000010111000 #
b00000000000000000000000010111000 %
1\
b00000000000000000000000010111100 e
#93
0\
#94
b00000000000000000000000010111100 #
b00000000000000000000000010111100 %
1\
b00000000000000000000000011000000 e
#95
0\
#96
b00000000000000000000000011000000 #
b00000000000000000000000011000000 %
1\
b00000000000000000000000011000100 e
#97
0\
#98
b00000000000000000000000011000100 #
b00000000000000000000000011000100 %
1\
b00000000000000000000000011001000 e
#99
0\
#100
b00000000000000000000000011001000 #
b00000000000000000000000011001000 %
1\
b00000000000000000000000011001100 e
#101
0\
#102
b00000000000000000000000011001100 #
b00000000000000000000000011001100 %
1\
b00000000000000000000000011010000 e
#103
0\
#104
b00000000000000000000000011010000 #
b00000000000000000000000011010000 %
1\
b00000000000000000000000011010100 e
#105
0\
#106
b00000000000000000000000011010100 #
b00000000000000000000000011010100 %
1\
b00000000000000000000000011011000 e
#107
0\
#108
b00000000000000000000000011011000 #
b00000000000000000000000011011000 %
1\
b00000000000000000000000011011100 e
#109
0\
#110
b00000000000000000000000011011100 #
b00000000000000000000000011011100 %
1\
b00000000000000000000000011100000 e
#111
0\
#112
b00000000000000000000000011100000 #
b00000000000000000000000011100000 %
1\
b00000000000000000000000011100100 e
#113
0\
#114
b00000000000000000000000011100100 #
b00000000000000000000000011100100 %
1\
b00000000000000000000000011101000 e
#115
0\
#116
b00000000000000000000000011101000 #
b00000000000000000000000011101000 %
1\
b00000000000000000000000011101100 e
#117
0\
#118
b00000000000000000000000011101100 #
b00000000000000000000000011101100 %
1\
b00000000000000000000000011110000 e
#119
0\
#120
b00000000000000000000000011110000 #
b00000000000000000000000011110000 %
1\
b00000000000000000000000011110100 e
#121
0\
#122
b00000000000000000000000011110100 #
b00000000000000000000000011110100 %
1\
b00000000000000000000000011111000 e
#123
0\
#124
b00000000000000000000000011111000 #
b00000000000000000000000011111000 %
1\
b00000000000000000000000011111100 e
#125
0\
#126
b00000000000000000000000011111100 #
b00000000000000000000000011111100 %
1\
b00000000000000000000000100000000 e
#127
0\
#128
b00000000000000000000000100000000 #
b00000000000000000000000100000000 %
1\
b00000000000000000000000100000100 e
#129
0\
#130
b00000000000000000000000100000100 #
b00000000000000000000000100000100 %
1\
b00000000000000000000000100001000 e
#131
0\
#132
b00000000000000000000000100001000 #
b00000000000000000000000100001000 %
1\
b00000000000000000000000100001100 e
#133
0\
#134
b00000000000000000000000100001100 #
b00000000000000000000000100001100 %
1\
b00000000000000000000000100010000 e
#135
0\
#136
b00000000000000000000000100010000 #
b00000000000000000000000100010000 %
1\
b00000000000000000000000100010100 e
#137
0\
#138
b00000000000000000000000100010100 #
b00000000000000000000000100010100 %
1\
b00000000000000000000000100011000 e
#139
0\
#140
b00000000000000000000000100011000 #
b00000000000000000000000100011000 %
1\
b00000000000000000000000100011100 e
#141
0\
#142
b00000000000000000000000100011100 #
b00000000000000000000000100011100 %
1\
b00000000000000000000000100100000 e
#143
0\
#144
b00000000000000000000000100100000 #
b00000000000000000000000100100000 %
1\
b00000000000000000000000100100100 e
#145
0\
#146
b00000000000000000000000100100100 #
b00000000000000000000000100100100 %
1\
b00000000000000000000000100101000 e
#147
0\
#148
b00000000000000000000000100101000 #
b00000000000000000000000100101000 %
1\
b00000000000000000000000100101100 e
#149
0\
#150
b00000000000000000000000100101100 #
b00000000000000000000000100101100 %
1\
b00000000000000000000000100110000 e
#151
0\
#152
b00000000000000000000000100110000 #
b00000000000000000000000100110000 %
1\
b00000000000000000000000100110100 e
#153
0\
#154
b00000000000000000000000100110100 #
b00000000000000000000000100110100 %
1\
b00000000000000000000000100111000 e
#155
0\
#156
b00000000000000000000000100111000 #
b00000000000000000000000100111000 %
1\
b00000000000000000000000100111100 e
#157
0\
#158
b00000000000000000000000100111100 #
b00000000000000000000000100111100 %
1\
b00000000000000000000000101000000 e
#159
0\
#160
b00000000000000000000000101000000 #
b00000000000000000000000101000000 %
1\
b00000000000000000000000101000100 e
#161
0\
#162
b00000000000000000000000101000100 #
b00000000000000000000000101000100 %
1\
b00000000000000000000000101001000 e
#163
0\
#164
b00000000000000000000000101001000 #
b00000000000000000000000101001000 %
1\
b00000000000000000000000101001100 e
#165
0\
#166
b00000000000000000000000101001100 #
b00000000000000000000000101001100 %
1\
b00000000000000000000000101010000 e
#167
0\
#168
b00000000000000000000000101010000 #
b00000000000000000000000101010000 %
1\
b00000000000000000000000101010100 e
#169
0\
#170
b00000000000000000000000101010100 #
b00000000000000000000000101010100 %
1\
b00000000000000000000000101011000 e
#171
0\
#172
b00000000000000000000000101011000 #
b00000000000000000000000101011000 %
1\
b00000000000000000000000101011100 e
#173
0\
#174
b00000000000000000000000101011100 #
b00000000000000000000000101011100 %
1\
b00000000000000000000000101100000 e
#175
0\
#176
b00000000000000000000000101100000 #
b00000000000000000000000101100000 %
1\
b00000000000000000000000101100100 e
#177
0\
#178
b00000000000000000000000101100100 #
b00000000000000000000000101100100 %
1\
b00000000000000000000000101101000 e
#179
0\
#180
b00000000000000000000000101101000 #
b00000000000000000000000101101000 %
1\
b00000000000000000000000101101100 e
#181
0\
#182
b00000000000000000000000101101100 #
b00000000000000000000000101101100 %
1\
b00000000000000000000000101110000 e
#183
0\
#184
b00000000000000000000000101110000 #
b00000000000000000000000101110000 %
1\
b00000000000000000000000101110100 e
#185
0\
#186
b00000000000000000000000101110100 #
b00000000000000000000000101110100 %
1\
b00000000000000000000000101111000 e
#187
0\
#188
b00000000000000000000000101111000 #
b00000000000000000000000101111000 %
1\
b00000000000000000000000101111100 e
#189
0\
#190
b00000000000000000000000101111100 #
b00000000000000000000000101111100 %
1\
b00000000000000000000000110000000 e
#191
0\
#192
b00000000000000000000000110000000 #
b00000000000000000000000110000000 %
1\
b00000000000000000000000110000100 e
#193
0\
#194
b00000000000000000000000110000100 #
b00000000000000000000000110000100 %
1\
b00000000000000000000000110001000 e
#195
0\
#196
b00000000000000000000000110001000 #
b00000000000000000000000110001000 %
1\
b00000000000000000000000110001100 e
#197
0\
#198
b00000000000000000000000110001100 #
b00000000000000000000000110001100 %
1\
b00000000000000000000000110010000 e
#199
0\
#200
b00000000000000000000000110010000 #
b00000000000000000000000110010000 %
1\
b00000000000000000000000110010100 e
#201
0\
#202
b00000000000000000000000110010100 #
b00000000000000000000000110010100 %
1\
b00000000000000000000000110011000 e
#203
0\
#204
b00000000000000000000000110011000 #
b00000000000000000000000110011000 %
1\
b00000000000000000000000110011100 e
#205
0\
